MANIFEST.in
README.rst
setup.py
Vinergy.egg-info/PKG-INFO
Vinergy.egg-info/SOURCES.txt
Vinergy.egg-info/dependency_links.txt
Vinergy.egg-info/requires.txt
Vinergy.egg-info/top_level.txt
tests/__init_.py
tests/vinergy_tests.py
tests/vinergy_tests.pyc
vinergy/__init__.py
vinergy/config.py
vinergy/model.py
vinergy/vinergy.py
vinergy/static/code.css
vinergy/static/code.js
vinergy/static/favicon.ico
vinergy/static/humans.txt
vinergy/static/mongodb.png
vinergy/static/pygments.png
vinergy/static/robots.txt
vinergy/static/webpy.png
vinergy/templates/base.html
vinergy/templates/code.html
vinergy/templates/index.html