Metadata-Version: 1.0
Name: Vinergy
Version: 0.3
Summary: Vinergy - CLI Pastebin within VimEnergy
Home-page: http://p.vim-cn.com
Author: Vayn
Author-email: vayn@vayn.de
License: GPL3
Download-URL: https://github.com/vayn/vinergy
Platform: UNKNOWN
Classifier: Development Status :: 4 - Beta
Classifier: Environment :: Web Environment
Classifier: Intended Audience :: Developers
Classifier: License :: OSI Approved :: GNU General Public License (GPL) 
Classifier: Operating System :: POSIX :: Linux
Classifier: Programming Language :: Python
Classifier: Topic :: Internet
